MANIFEST.in
README.rst
setup.py
docs/HISTORY.rst
docs/INSTALL.txt
docs/LICENSE.GPL
docs/LICENSE.txt
unipdgest/__init__.py
unipdgest.portlet.navigation.egg-info/PKG-INFO
unipdgest.portlet.navigation.egg-info/SOURCES.txt
unipdgest.portlet.navigation.egg-info/dependency_links.txt
unipdgest.portlet.navigation.egg-info/entry_points.txt
unipdgest.portlet.navigation.egg-info/namespace_packages.txt
unipdgest.portlet.navigation.egg-info/not-zip-safe
unipdgest.portlet.navigation.egg-info/requires.txt
unipdgest.portlet.navigation.egg-info/top_level.txt
unipdgest/portlet/__init__.py
unipdgest/portlet/navigation/__init__.py
unipdgest/portlet/navigation/accordion_navigation.pt
unipdgest/portlet/navigation/accordion_navigation_recurse.pt
unipdgest/portlet/navigation/accordionnavigationportlet.py
unipdgest/portlet/navigation/configure.zcml
unipdgest/portlet/navigation/query_builder.py
unipdgest/portlet/navigation/locales/rebuildPo.sh
unipdgest/portlet/navigation/locales/unipdgest.portlet.navigation-manual.pot
unipdgest/portlet/navigation/locales/unipdgest.portlet.navigation.pot
unipdgest/portlet/navigation/locales/it/LC_MESSAGES/unipdgest.portlet.navigation.mo
unipdgest/portlet/navigation/locales/it/LC_MESSAGES/unipdgest.portlet.navigation.po
unipdgest/portlet/navigation/profiles/default/cssregistry.xml
unipdgest/portlet/navigation/profiles/default/jsregistry.xml
unipdgest/portlet/navigation/profiles/default/metadata.xml
unipdgest/portlet/navigation/profiles/default/portlets.xml
unipdgest/portlet/navigation/resources/accordion.css
unipdgest/portlet/navigation/resources/accordion.js
unipdgest/portlet/navigation/resources/minus.png
unipdgest/portlet/navigation/resources/plus.png