Metadata-Version: 1.0
Name: unipdgest.portlet.navigation
Version: 0.1.0
Summary: Plone navigation portlet with accordion
Home-page: http://bitbucket.org/redturtle/unipdgest.portlet.navigation
Author: RedTurtle Technology
Author-email: sviluppoplone@redturtle.it
License: GPL
Keywords: plone navigation accordion
Platform: UNKNOWN
Classifier: Framework :: Plone
Classifier: Framework :: Plone :: 4.3
Classifier: Programming Language :: Python
